LICENSE.txt
README.md
setup.cfg
setup.py
AztVe/__init__.py
AztVeClient.egg-info/PKG-INFO
AztVeClient.egg-info/SOURCES.txt
AztVeClient.egg-info/dependency_links.txt
AztVeClient.egg-info/requires.txt
AztVeClient.egg-info/top_level.txt
AztVe/common/__init__.py
AztVe/common/azt_errors.py
AztVe/common/azt_logger.py
AztVe/common/qujam_buffer.py
AztVe/common/qujam_func_switch.py
AztVe/common/qujam_heart_beat.py
AztVe/common/qujam_socket.py
AztVe/common/qujam_socket_zmq.py
AztVe/common/qujam_struct_for_azt.py
AztVe/common/utils.py
AztVe/protos/EnumType_pb2.py
AztVe/protos/MsgType_pb2.py
AztVe/protos/Quote_Message_pb2.py
AztVe/protos/Trade_Message_pb2.py
AztVe/protos/UnitedMessage_pb2.py
AztVe/protos/__init__.py
AztVe/src/__init__.py
AztVe/src/quote_api/__init__.py
AztVe/src/quote_api/_quote_api_base.py
AztVe/src/quote_api/quote_api.py
AztVe/src/quote_api/quote_spi.py
AztVe/src/trade_api/__init__.py
AztVe/src/trade_api/_trade_api_base.py
AztVe/src/trade_api/trade_api.py
AztVe/src/trade_api/trade_spi.py
AztVe/structs/__init__.py
AztVe/structs/quote_spi_struct.py
AztVe/structs/trade_api_struct.py
AztVe/structs/trade_spi_struct.py