Metadata-Version: 1.1
Name: AztVeClient
Version: 1.0.0.post1
Summary: AztQuant Virtual Exchange And Quote Server Python Client
Home-page: https://gitee.com/Qujamlee/azt-ve-client
Author: Qujamlee
Author-email: qujamlee@126.com
License: GNU Lesser General Public License v3.0
Download-URL: https://gitee.com/Qujamlee/azt-ve-client
Keywords: azt,aztve
Platform: UNKNOWN
Classifier: Development Status :: 4 - Beta
Classifier: Intended Audience :: Developers
Classifier: Topic :: Software Development :: Build Tools
Classifier: License :: OSI Approved :: GNU Lesser General Public License v3 or later (LGPLv3+)
Classifier: Programming Language :: Python :: 3.7
Classifier: Programming Language :: Python :: 3.8
Classifier: Programming Language :: Python :: 3.9
Classifier: Programming Language :: Python :: 3.10
